build/__init__.py
build/builder.py
euba/__init__.py
euba/build/__init__.py
euba/build/builder.py
euba/establish/__init__.py
euba/establish/builder.py
euba-0.1.2.dist-info/LICENSE
euba-0.1.2.dist-info/METADATA
euba-0.1.2.dist-info/WHEEL
euba-0.1.2.dist-info/top_level.txt
euba-0.1.2.dist-info/RECORD
